degiro_pit/__init__.py
degiro_pit/config.py
degiro_pit/date_tax.py
degiro_pit/enricher.py
degiro_pit/nbp_api.py
tests/__init__.py
tests/test_date_tax_poland.py
tests/test_degiro_pit_config.py
tests/test_nbp_api.py
degiro_pit_woj_i-0.3.0.dist-info/LICENSE
degiro_pit_woj_i-0.3.0.dist-info/METADATA
degiro_pit_woj_i-0.3.0.dist-info/WHEEL
degiro_pit_woj_i-0.3.0.dist-info/entry_points.txt
degiro_pit_woj_i-0.3.0.dist-info/top_level.txt
degiro_pit_woj_i-0.3.0.dist-info/RECORD
