Metadata-Version: 2.1
Name: degiro-pit-woj-i
Version: 0.3.0
Summary: Application for get PLN value of a currency for the last working day before DeGiro transaction. It helps to prepare PIT for The National Revenue Administration
Home-page: https://github.com/woj-i/degiro-pit/
Author: Wojciech Indyk
License: UNKNOWN
Platform: UNKNOWN
Classifier: Programming Language :: Python :: 3
Classifier: License :: OSI Approved :: MIT License
Classifier: Operating System :: OS Independent
Requires-Python: >=3.8
Requires-Dist: pandas (==1.2.1)
Requires-Dist: holidays (>=0.10.5.2)
